[
  {
    "id": "t1",
    "title": "Full Body Beginner",
    "duration": 30,
    "level": "Beginner",
    "category": "Full Body",
    "exercises": [
      { "id": "e1", "name": "Agachamento", "reps": "3x12", "rest": "60s" },
      { "id": "e2", "name": "Flexão de braço", "reps": "3x10", "rest": "60s" },
      { "id": "e3", "name": "Prancha", "reps": "3x30s", "rest": "45s" },
      { "id": "e4", "name": "Afundo", "reps": "3x10 cada", "rest": "60s" },
      { "id": "e5", "name": "Abdominal", "reps": "3x20", "rest": "45s" }
    ]
  },
  {
    "id": "t2",
    "title": "Upper Body Strength",
    "duration": 45,
    "level": "Intermediate",
    "category": "Força",
    "exercises": [
      { "id": "e6", "name": "Barra fixa", "reps": "4x6", "rest": "90s" },
      { "id": "e7", "name": "Remada haltere", "reps": "4x8", "rest": "75s" },
      { "id": "e8", "name": "Supino halteres", "reps": "4x10", "rest": "75s" },
      { "id": "e9", "name": "Desenvolvimento ombros", "reps": "3x10", "rest": "60s" },
      { "id": "e10", "name": "Tríceps corda", "reps": "3x12", "rest": "60s" }
    ]
  },
  {
    "id": "t3",
    "title": "HIIT Cardio Burn",
    "duration": 25,
    "level": "Advanced",
    "category": "HIIT",
    "exercises": [
      { "id": "e11", "name": "Burpee", "reps": "4x10", "rest": "30s" },
      { "id": "e12", "name": "Jumping Jack", "reps": "4x30s", "rest": "15s" },
      { "id": "e13", "name": "Mountain Climber", "reps": "4x20", "rest": "20s" },
      { "id": "e14", "name": "Sprint estacionário", "reps": "4x30s", "rest": "15s" }
    ]
  },
  {
    "id": "t4",
    "title": "Lower Body Power",
    "duration": 40,
    "level": "Intermediate",
    "category": "Pernas",
    "exercises": [
      { "id": "e15", "name": "Leg press", "reps": "4x12", "rest": "75s" },
      { "id": "e16", "name": "Cadeira extensora", "reps": "3x15", "rest": "60s" },
      { "id": "e17", "name": "Cadeira flexora", "reps": "3x15", "rest": "60s" },
      { "id": "e18", "name": "Panturrilha em pé", "reps": "4x20", "rest": "45s" },
      { "id": "e19", "name": "Agachamento sumô", "reps": "3x12", "rest": "60s" }
    ]
  },
  {
    "id": "t5",
    "title": "Core & Mobilidade",
    "duration": 20,
    "level": "Beginner",
    "category": "Funcional",
    "exercises": [
      { "id": "e20", "name": "Prancha lateral", "reps": "3x20s cada", "rest": "30s" },
      { "id": "e21", "name": "Dead bug", "reps": "3x10", "rest": "30s" },
      { "id": "e22", "name": "Hip thrust", "reps": "3x15", "rest": "60s" },
      { "id": "e23", "name": "Gato-vaca", "reps": "3x10", "rest": "30s" }
    ]
  }
]
